{
    "filename": "CBVtLQogcw0.jpg",
    "description": "Wir haben einem unserer Praktikanten LSD gegeben. Kannst du seine Aussagen von Attila Hildmanns unterscheiden? #quiz\u2800\n.\u2800\u2800\nVerlinkung zu diesem und allen weiteren Artikeln: Klick den Link in der Bio\u261d\ud83c\udffcMehr seri\u00f6se Nachrichten auf https://www.der-postillon.com\u2800\u2800\n.\u2800\u2800\u2800\u2800\u2800\n#postillon #attilahildmann #hildmann",
    "label": "attilahildmann",
    "tags": [
        "quiz",
        "postillon",
        "attilahildmann",
        "hildmann"
    ],
    "year": "6"
}