{
    "filename": "CCEzQGWA_0z.jpg",
    "description": "For those who aren't yet aware, this is what \ud83e\udd8e\ud83e\udd8e\ud83e\udd8e \"\"Adrenochrome Withdrawal\"\" looks like. In 2018, Trump cut-off their satanic supply of harvested young blood. \ud83d\ude22 \n#andrenochrome #cosmetic #adrenochromejunkies #adrenochromewithdrawals #AdrenochromeHarvesting #childabuse #mutilation  #hollywoodisdead #cannibals #Pedowood #shrinkingviolet #celebritiesaredying #cabal #torture #spiritcooking #satanicrituals #satanicelite #PizzaGate #Frazzledrip #CrimesAgainstChildren #CrimesAgainstHumanity #CrimesAgainstAmerica",
    "label": "andrenochrome",
    "tags": [
        "andrenochrome",
        "cosmetic",
        "adrenochromejunkies",
        "adrenochromewithdrawals",
        "adrenochromeharvesting",
        "childabuse",
        "mutilation",
        "hollywoodisdead",
        "cannibals",
        "pedowood",
        "shrinkingviolet",
        "celebritiesaredying",
        "cabal",
        "torture",
        "spiritcooking",
        "satanicrituals",
        "satanicelite",
        "pizzagate",
        "frazzledrip",
        "crimesagainstchildren",
        "crimesagainsthumanity",
        "crimesagainstamerica"
    ],
    "year": "6"
}